Workbook

Sheet Financial Data
A1: Target Corporation ($ millions) | B1: 2019 | C1: 2020 | D1: 2021 | E1: 2022 | F1: 2023 | G1: 2024
A3: Income Statement
A4: Sales | B4: 77130 | C4: 92400 | D4: 104611 | E4: 107588 | F4: 105803 | G4: 106566
A5: Cost of Sales | B5: 54864 | C5: 66177 | D5: 74963 | E5: 82229 | F5: 77736 | G5: 76502
A6: Gross Profit | B6: =B4-B5 -> 22266 | C6: =C4-C5 -> 26223 | D6: =D4-D5 -> 29648 | E6: =E4-E5 -> 25359 | F6: =F4-F5 -> 28067 | G6: =G4-G5 -> 30064
A7: Operating Income | B7: 4658 | C7: 6539 | D7: 8946 | E7: 3848 | F7: 5707 | G7: 5566
A8: Net Earnings | B8: 3281 | C8: 4368 | D8: 6946 | E8: 2780 | F8: 4138 | G8: 4091
A9: Net Interest Expense | B9: 477 | C9: 977 | D9: 421 | E9: 478 | F9: 502 | G9: 411
A10: Balance Sheet
A11: Cash & Cash Equivalents | B11: 2577 | C11: 8511 | D11: 5911 | E11: 2229 | F11: 3805 | G11: 4762
A12: Inventory | B12: 8992 | C12: 10653 | D12: 13902 | E12: 13499 | F12: 11886 | G12: 12740
A13: Other Current Assets | B13: 1333 | C13: 1592 | D13: 1760 | E13: 2118 | F13: 1807 | G13: 1952
A14: Total Current Assets | B14: 12902 | C14: 20756 | D14: 21573 | E14: 17846 | F14: 17498 | G14: 19454
A15: Total Current Libailities | B15: 14487 | C15: 20125 | D15: 21747 | E15: 19500 | F15: 19304 | G15: 20799
A16: Total Assets | B16: 42779 | C16: 51248 | D16: 53811 | E16: 53335 | F16: 55356 | G16: 57769
A17: Shareholders' Equity | B17: 11833 | C17: 14440 | D17: 12827 | E17: 11232 | F17: 13432 | G17: 14666
A18: Accounts Payable | B18: 9920 | C18: 12859 | D18: 15478 | E18: 13487 | F18: 12098 | G18: 13053
A19: Current Debt/Borrowings | B19: 161 | C19: 1144 | D19: 171 | E19: 130 | F19: 1116 | G19: 1636
A21: Source: Target Corporation Forms 10-K, SEC EDGAR, fiscal years 2020-2024

Sheet Liquidity
A1: Liquidity Ratios | B1: 2020 | C1: 2021 | D1: 2022 | E1: 2023 | F1: 2024
A3: Current Ratio | B3: ='Financial Data'!C14/'Financial Data'!C15 -> 1.031354 | C3: ='Financial Data'!D14/'Financial Data'!D15 -> 0.9919989 | D3: ='Financial Data'!E14/'Financial Data'!E15 -> 0.91517949 | E3: ='Financial Data'!F14/'Financial Data'!F15 -> 0.90644426 | F3: ='Financial Data'!G14/'Financial Data'!G15 -> 0.93533343
A4: Acid Test Ratio | B4: =('Financial Data'!C14-'Financial Data'!C12)/'Financial Data'!C15 -> 0.50201242 | C4: =('Financial Data'!D14-'Financial Data'!D12)/'Financial Data'!D15 -> 0.35273831 | D4: =('Financial Data'!E14-'Financial Data'!E12)/'Financial Data'!E15 -> 0.22292308 | E4: =('Financial Data'!F14-'Financial Data'!F12)/'Financial Data'!F15 -> 0.29071695 | F4: =('Financial Data'!G14-'Financial Data'!G12)/'Financial Data'!G15 -> 0.32280398
A5: Cash Ratio | B5: ='Financial Data'!C11/'Financial Data'!C15 -> 0.42290683 | C5: ='Financial Data'!D11/'Financial Data'!D15 -> 0.27180761 | D5: ='Financial Data'!E11/'Financial Data'!E15 -> 0.11430769 | E5: ='Financial Data'!F11/'Financial Data'!F15 -> 0.19710941 | F5: ='Financial Data'!G11/'Financial Data'!G15 -> 0.22895332
A7: Source: Target Corporation Forms 10-K, SEC EDGAR, fiscal years 2020-2024

Sheet Efficiency
A1: Efficiency Ratios | B1: 2020 | C1: 2021 | D1: 2022 | E1: 2023 | F1: 2024
A3: Total Asset Turnover | B3: ='Financial Data'!C4/ (('Financial Data'!C16 + 'Financial Data'!B16)/2) -> 1.9653929 | C3: ='Financial Data'!D4/ (('Financial Data'!D16 + 'Financial Data'!C16)/2) -> 1.9914715 | D3: ='Financial Data'!E4/ (('Financial Data'!E16 + 'Financial Data'!D16)/2) -> 2.0082504 | E3: ='Financial Data'!F4/ (('Financial Data'!F16 + 'Financial Data'!E16)/2) -> 1.9468585 | F3: ='Financial Data'!G4/ (('Financial Data'!G16 + 'Financial Data'!F16)/2) -> 1.8840398
A4: Inventory Turnover | B4: ='Financial Data'!C5/ (('Financial Data'!C12 + 'Financial Data'!B12)/2) -> 6.7372868 | C4: ='Financial Data'!D5/ (('Financial Data'!D12 + 'Financial Data'!C12)/2) -> 6.1057218 | D4: ='Financial Data'!E5/ (('Financial Data'!E12 + 'Financial Data'!D12)/2) -> 6.0018977 | E4: ='Financial Data'!F5/ (('Financial Data'!F12 + 'Financial Data'!E12)/2) -> 6.1245617 | F4: ='Financial Data'!G5/ (('Financial Data'!G12 + 'Financial Data'!F12)/2) -> 6.2131081
A5: Days Inventory Outstanding | B5: =365 / B4 -> 54.176111 | C5: =365 / C4 -> 59.779991 | D5: =365 / D4 -> 60.814098 | E5: =365 / E4 -> 59.596101 | F5: =365 / F4 -> 58.746765
A6: Accounts Receivable Turnover | B6: ='Financial Data'!C4/ (('Financial Data'!C13 + 'Financial Data'!B13)/2) -> 63.179487 | C6: ='Financial Data'!D4/ (('Financial Data'!D13 + 'Financial Data'!C13)/2) -> 62.417064 | D6: ='Financial Data'!E4/ (('Financial Data'!E13 + 'Financial Data'!D13)/2) -> 55.486333 | E6: ='Financial Data'!F4/ (('Financial Data'!F13 + 'Financial Data'!E13)/2) -> 53.912357 | F6: ='Financial Data'!G4/ (('Financial Data'!G13 + 'Financial Data'!F13)/2) -> 56.699122
A7: Average Collection Period | B7: =365 / B6 -> 5.7771916 | C7: =365 / C6 -> 5.8477598 | D7: =365 / D6 -> 6.5781965 | E7: =365 / E6 -> 6.7702475 | F7: =365 / F6 -> 6.4374894
A8: Accounts Payable Turnover | B8: ='Financial Data'!C5/ (('Financial Data'!C18 + 'Financial Data'!B18)/2) -> 5.8103516 | C8: ='Financial Data'!D5/ (('Financial Data'!D18 + 'Financial Data'!C18)/2) -> 5.2908212 | D8: ='Financial Data'!E5/ (('Financial Data'!E18 + 'Financial Data'!D18)/2) -> 5.6778181 | E8: ='Financial Data'!F5/ (('Financial Data'!F18 + 'Financial Data'!E18)/2) -> 6.0766856 | F8: ='Financial Data'!G5/ (('Financial Data'!G18 + 'Financial Data'!F18)/2) -> 6.0834162
A9: Average Payment Period | B9: =365 / B8 -> 62.818917 | C9: =365 / C8 -> 68.9874 | D9: =365 / D8 -> 64.285258 | E9: =365 / E8 -> 60.065639 | F9: =365 / F8 -> 59.999183
A10: Operating Cycle | B10: =B5 + B7 -> 59.953303 | C10: =C5 + C7 -> 65.627751 | D10: =D5 + D7 -> 67.392295 | E10: =E5 + E7 -> 66.366348 | F10: =F5 + F7 -> 65.184254
A11: Cash Conversion Cycle | B11: =B10 - B9 -> -2.8656149 | C11: =C10 - C9 -> -3.3596492 | D11: =D10 - D9 -> 3.1070366 | E11: =E10 - E9 -> 6.3007096 | F11: =F10 - F9 -> 5.1850712
A13: Source: Target Corporation Forms 10-K, SEC EDGAR, fiscal years 2020-2024

Sheet Profitability
A1: Profitability Ratios | B1: 2020 | C1: 2021 | D1: 2022 | E1: 2023 | F1: 2024
A3: Gross Profit Margin | B3: ='Financial Data'!C6/'Financial Data'!C4 -> 0.2837987 | C3: ='Financial Data'!D6/'Financial Data'!D4 -> 0.28341188 | D3: ='Financial Data'!E6/'Financial Data'!E4 -> 0.23570473 | E3: ='Financial Data'!F6/'Financial Data'!F4 -> 0.26527603 | F3: ='Financial Data'!G6/'Financial Data'!G4 -> 0.28211625
A4: Operating Profit Margin | B4: ='Financial Data'!C7/'Financial Data'!C4 -> 0.070768398 | C4: ='Financial Data'!D7/'Financial Data'!D4 -> 0.085516819 | D4: ='Financial Data'!E7/'Financial Data'!E4 -> 0.035766071 | E4: ='Financial Data'!F7/'Financial Data'!F4 -> 0.053939869 | F4: ='Financial Data'!G7/'Financial Data'!G4 -> 0.052230543
A5: Net Profit Margin | B5: ='Financial Data'!C8/'Financial Data'!C4 -> 0.047272727 | C5: ='Financial Data'!D8/'Financial Data'!D4 -> 0.066398371 | D5: ='Financial Data'!E8/'Financial Data'!E4 -> 0.025839313 | E5: ='Financial Data'!F8/'Financial Data'!F4 -> 0.039110422 | F5: ='Financial Data'!G8/'Financial Data'!G4 -> 0.038389355
A6: Operating Return on Assets | B6: ='Financial Data'!C7/'Financial Data'!C16 -> 0.12759522 | C6: ='Financial Data'!D7/'Financial Data'!D16 -> 0.16624854 | D6: ='Financial Data'!E7/'Financial Data'!E16 -> 0.072147745 | E6: ='Financial Data'!F7/'Financial Data'!F16 -> 0.10309632 | F6: ='Financial Data'!G7/'Financial Data'!G16 -> 0.096349253
A7: Return on Equity (ROE) | B7: ='Financial Data'!C8/'Financial Data'!C17 -> 0.30249307 | C7: ='Financial Data'!D8/'Financial Data'!D17 -> 0.54151399 | D7: ='Financial Data'!E8/'Financial Data'!E17 -> 0.24750712 | E7: ='Financial Data'!F8/'Financial Data'!F17 -> 0.30807028 | F7: ='Financial Data'!G8/'Financial Data'!G17 -> 0.2789445
A8: Return on Assets (ROA) | B8: ='Financial Data'!C8/'Financial Data'!C16 -> 0.085232594 | C8: ='Financial Data'!D8/'Financial Data'!D16 -> 0.12908141 | D8: ='Financial Data'!E8/'Financial Data'!E16 -> 0.052123371 | E8: ='Financial Data'!F8/'Financial Data'!F16 -> 0.074752511 | F8: ='Financial Data'!G8/'Financial Data'!G16 -> 0.070816528
A10: Source: Target Corporation Forms 10-K, SEC EDGAR, fiscal years 2020-2024

Sheet Market
A1: Market Ratios
B3: FY2020 | C3: FY2021 | D3: FY2022 | E3: FY2023 | F3: 2024
A4: Price date | B4: Jan 29th, 2021 | C4: Jan 28th, 2022 | D4: Jan 27th, 2023 | E4: Feb 2,2024 | F4: Jan 31,2025
A5: Stock price | B5: 181.17 | C5: 217.67 | D5: 168.51 | E5: 145.49 | F5: 137.91
A6: Diluted EPS | B6: 8.64 | C6: 14.1 | D6: 5.98 | E6: 8.94 | F6: 8.86
A7: Outstanding shares | B7: 500.9 | C7: 471.3 | D7: 460.3 | E7: 461.7 | F7: 455.6
A8: Total stockholders equity | B8: 14440 | C8: 12827 | D8: 11232 | E8: 13432 | F8: 14666
A10: Calculations | G10: Formula
A12: Book value per share | B12: =B8/B7 -> 28.828109 | C12: =C8/C7 -> 27.21621 | D12: =D8/D7 -> 24.401477 | E12: =E8/E7 -> 29.092484 | F12: =F8/F7 -> 32.190518 | G12: stockholder's equity/ outstanding shares
A13: Market cap ( millions) | B13: =B5*B7 -> 90748.053 | C13: =C5*C7 -> 102587.87 | D13: =D5*D7 -> 77565.153 | E13: =E5*E7 -> 67172.733 | F13: =F5*F7 -> 62831.796 | G13: Stock price * outstanding shares
A14: Price to earning | B14: =B5/B6 -> 20.96875 | C14: =C5/C6 -> 15.437589 | D14: =D5/D6 -> 28.17893 | E14: =E5/E6 -> 16.274049 | F14: =F5/F6 -> 15.565463 | G14: stock price / diluted EPS
A15: price to book | B15: =B5/B12 -> 6.2844912 | C15: =C5/C12 -> 7.997807 | D15: =D5/D12 -> 6.9057294 | E15: =E5/E12 -> 5.000948 | F15: =F5/F12 -> 4.2841808 | G15: Stock price/ Book value per share
A16: Market to book | B16: =B13/B8 -> 6.2844912 | C16: =C13/C8 -> 7.997807 | D16: =D13/D8 -> 6.9057294 | E16: =E13/E8 -> 5.000948 | F16: =F13/F8 -> 4.2841808 | G16: Market cap / Stockholder's equity
A18: Sources
A19: Target Corporation Forms 10-K, fiscal years 2020–2024, SEC EDGAR
A20: Yahoo finance ( closing stock prices)

Sheet DuPont
A1: DuPont Analysis | B1: 2020 | C1: 2021 | D1: 2022 | E1: 2023 | F1: 2024
A2: Profit Margin | B2: ='Financial Data'!C8/'Financial Data'!C4 -> 0.047272727 | C2: ='Financial Data'!D8/'Financial Data'!D4 -> 0.066398371 | D2: ='Financial Data'!E8/'Financial Data'!E4 -> 0.025839313 | E2: ='Financial Data'!F8/'Financial Data'!F4 -> 0.039110422 | F2: ='Financial Data'!G8/'Financial Data'!G4 -> 0.038389355
A3: Total Asset Turnover | B3: ='Financial Data'!C4/'Financial Data'!C16 -> 1.8029972 | C3: ='Financial Data'!D4/'Financial Data'!D16 -> 1.9440449 | D3: ='Financial Data'!E4/'Financial Data'!E16 -> 2.017212 | E3: ='Financial Data'!F4/'Financial Data'!F16 -> 1.9113195 | F3: ='Financial Data'!G4/'Financial Data'!G16 -> 1.8446918
A4: Return on Assets | B4: =B2*B3 -> 0.085232594 | C4: =C2*C3 -> 0.12908141 | D4: =D2*D3 -> 0.052123371 | E4: =E2*E3 -> 0.074752511 | F4: =F2*F3 -> 0.070816528
A5: Debt/Assets | B5: =('Financial Data'!C16-'Financial Data'!C17)/'Financial Data'!C16 -> 0.71823291 | C5: =('Financial Data'!D16-'Financial Data'!D17)/'Financial Data'!D16 -> 0.76162866 | D5: =('Financial Data'!E16-'Financial Data'!E17)/'Financial Data'!E16 -> 0.78940658 | E5: =('Financial Data'!F16-'Financial Data'!F17)/'Financial Data'!F16 -> 0.75735241 | F5: =('Financial Data'!G16-'Financial Data'!G17)/'Financial Data'!G16 -> 0.74612682
A6: 1-Debt/Assets | B6: =1-B5 -> 0.28176709 | C6: =1-C5 -> 0.23837134 | D6: =1-D5 -> 0.21059342 | E6: =1-E5 -> 0.24264759 | F6: =1-F5 -> 0.25387318
A7: Return on Equity | B7: =B4/B6 -> 0.30249307 | C7: =C4/C6 -> 0.54151399 | D7: =D4/D6 -> 0.24750712 | E7: =E4/E6 -> 0.30807028 | F7: =F4/F6 -> 0.2789445
A9: Source: Target Corporation Forms 10-K, SEC EDGAR, fiscal years 2020-2024

Sheet Debt 
A1: Debt Analysis
B3: 2020 | C3: 2021 | D3: 2022 | E3: 2023 | F3: 2024
A4: Total assets ( millions) | B4: 51248 | C4: 53811 | D4: 53335 | E4: 55356 | F4: 57769
A5: Total current liabilites | B5: 20125 | C5: 21747 | D5: 19500 | E5: 19304 | F5: 20799
A6: Stockholders equity | B6: 14440 | C6: 12827 | D6: 11232 | E6: 13432 | F6: 14666
A7: Operating income | B7: 6539 | C7: 8946 | D7: 3848 | E7: 5707 | F7: 5566
A8: Net interest expense | B8: 977 | C8: 421 | D8: 478 | E8: 502 | F8: 411
A10: Calculations | G10: Formula
A12: Total liabilities | B12: =B4-B6 -> 36808 | C12: =C4-C6 -> 40984 | D12: =D4-D6 -> 42103 | E12: =E4-E6 -> 41924 | F12: =F4-F6 -> 43103 | G12: Total assets- stockholder equity
A13: Debt ratio | B13: =B12/B4 -> 0.71823291 | C13: =C12/C4 -> 0.76162866 | D13: =D12/D4 -> 0.78940658 | E13: =E12/E4 -> 0.75735241 | F13: =F12/F4 -> 0.74612682 | G13: total liabilities / total assets
A14: Short term debt ratio | B14: =B5/B12 -> 0.54675614 | C14: =C5/C12 -> 0.53062171 | D14: =D5/D12 -> 0.46314989 | E14: =E5/E12 -> 0.46045225 | F14: =F5/F12 -> 0.48254182 | G14: Total current liabilities / total liabilities
A15: Times intrest earned | B15: =B7/B8 -> 6.6929376 | C15: =C7/C8 -> 21.249406 | D15: =D7/D8 -> 8.0502092 | E15: =E7/E8 -> 11.368526 | F15: =F7/F8 -> 13.542579 | G15: operationg income / net intrest expense
A17: Sources
A18: Target Corporation Forms 10-K, fiscal years 2020–2024, SEC EDGAR
